oxidd-0.11.1.dist-info/METADATA
oxidd-0.11.1.dist-info/WHEEL
oxidd-0.11.1.dist-info/licenses/LICENSE-APACHE
oxidd-0.11.1.dist-info/licenses/LICENSE-MIT
oxidd/.gitignore
oxidd/__init__.py
oxidd/_oxidd.abi3.so
oxidd/bcdd.py
oxidd/bdd.py
oxidd/protocols.py
oxidd/py.typed
oxidd/tests/test_boolean_function.py
oxidd/util.py
oxidd/zbdd.py
oxidd-0.11.1.dist-info/RECORD
