Metadata-Version: 2.4
Name: oxidd
Version: 0.11.1
Classifier: Development Status :: 4 - Beta
Classifier: License :: OSI Approved :: MIT License
Classifier: License :: OSI Approved :: Apache Software License
Classifier: Programming Language :: C
Classifier: Programming Language :: C++
Classifier: Programming Language :: Python :: 3
Classifier: Programming Language :: Python :: 3 :: Only
Classifier: Programming Language :: Python :: 3.9
Classifier: Programming Language :: Python :: 3.10
Classifier: Programming Language :: Python :: 3.11
Classifier: Programming Language :: Python :: 3.12
Classifier: Programming Language :: Python :: 3.13
Classifier: Programming Language :: Rust
Classifier: Topic :: Scientific/Engineering
Classifier: Typing :: Typed
Requires-Dist: typing-extensions~=4.0
Requires-Dist: mypy==1.16.1 ; extra == 'dev'
Requires-Dist: basedpyright~=1.31 ; extra == 'dev'
Requires-Dist: ruff~=0.13 ; extra == 'dev'
Requires-Dist: sphinx~=8.0 ; extra == 'docs'
Requires-Dist: pydata-sphinx-theme~=0.16 ; extra == 'docs'
Requires-Dist: pytest>=8.0 ; extra == 'test'
Provides-Extra: dev
Provides-Extra: docs
Provides-Extra: test
License-File: LICENSE-APACHE
License-File: LICENSE-MIT
Summary: Decision Diagrams
Keywords: Decision Diagrams,BDD,ZBDD,ZDD
Home-Page: https://oxidd.net
Author-email: OxiDD Contributors <info@oxidd.net>
Maintainer-email: Nils Husung <nils@oxidd.net>
Requires-Python: >=3.9
Project-URL: Homepage, https://oxidd.net
Project-URL: Documentation, https://oxidd.net/api/python/dev/getting-started.html
Project-URL: Repository, https://github.com/OxiDD/oxidd
Project-URL: Issues, https://github.com/OxiDD/oxidd/issues
